fastapi_framework/__init__.py
fastapi_framework/config.py
fastapi_framework/database.py
fastapi_framework/in_memory_backend.py
fastapi_framework/jwt_auth.py
fastapi_framework/logger.py
fastapi_framework/modules.py
fastapi_framework/permissions.py
fastapi_framework/rate_limit.py
fastapi_framework/redis.py
fastapi_framework/session.py
fastapi_framework/settings.py
fastapi_framework-1.5.3.5.dist-info/LICENSE
fastapi_framework-1.5.3.5.dist-info/WHEEL
fastapi_framework-1.5.3.5.dist-info/METADATA
fastapi_framework-1.5.3.5.dist-info/RECORD
