Metadata-Version: 2.1
Name: fastapi-framework
Version: 1.5.3.5
Summary: A FastAPI Framework for things like Database, Redis, Logging, JWT Authentication and Rate Limits
Author: Tert0
Requires-Python: >=3.6
Classifier: License :: OSI Approved :: MIT License
Classifier: Framework :: AsyncIO
Classifier: Intended Audience :: Developers
Classifier: Operating System :: POSIX :: Linux
Classifier: Programming Language :: Python :: 3.9
Classifier: Programming Language :: Python :: Implementation :: CPython
Classifier: Topic :: Database
Classifier: Topic :: Software Development :: Libraries
Classifier: Topic :: Software Development :: Libraries :: Python Modules
Classifier: Typing :: Typed
Requires-Dist: fastapi==0.103.2
Requires-Dist: aioredis==1.3.1
Requires-Dist: passlib==1.7.4
Requires-Dist: PyJWT==2.8.0
Requires-Dist: python-dotenv==1.0.0
Requires-Dist: SQLAlchemy==2.0.21
Requires-Dist: pyyaml==6.0.1
Requires-Dist: toml==0.10.2
Requires-Dist: pydantic==2.4.2
Requires-Dist: mkdocs-material ; extra == "doc"
Requires-Dist: black ; extra == "lint"
Requires-Dist: flake8 ; extra == "lint"
Requires-Dist: mypy ; extra == "lint"
Requires-Dist: types-PyYAML ; extra == "lint"
Requires-Dist: types-toml ; extra == "lint"
Requires-Dist: httpx ; extra == "test"
Requires-Dist: coverage ; extra == "test"
Requires-Dist: aiosqlite ; extra == "test"
Project-URL: Documentation, https://tert0.github.io/fastapi-framework
Project-URL: Source, https://github.com/Tert0/fastapi-framework
Provides-Extra: doc
Provides-Extra: lint
Provides-Extra: test
